{"CONCEPT_ID":[40762638],"CDM_TABLE_NAME":["MEASUREMENT"],"CONCEPT_NAME":["Body mass index (BMI) [Percentile] Per age and sex"],"NUM_PERSONS":[51],"PERCENT_PERSONS":["0.4679"],"RECORDS_PER_PERSON":[" 10.6"],"PREVALENCE_BY_GENDER_AGE_YEAR":[{"TRELLIS_NAME":"10-19","SERIES_NAME":"FEMALE","X_CALENDAR_YEAR":1974,"Y_PREVALENCE_1000PP":166.6667},{"TRELLIS_NAME":"10-19","SERIES_NAME":"FEMALE","X_CALENDAR_YEAR":1975,"Y_PREVALENCE_1000PP":142.8571},{"TRELLIS_NAME":"10-19","SERIES_NAME":"FEMALE","X_CALENDAR_YEAR":1976,"Y_PREVALENCE_1000PP":125},{"TRELLIS_NAME":"10-19","SERIES_NAME":"FEMALE","X_CALENDAR_YEAR":1977,"Y_PREVALENCE_1000PP":125},{"TRELLIS_NAME":"0-9","SERIES_NAME":"FEMALE","X_CALENDAR_YEAR":2003,"Y_PREVALENCE_1000PP":1000},{"TRELLIS_NAME":"0-9","SERIES_NAME":"FEMALE","X_CALENDAR_YEAR":2004,"Y_PREVALENCE_1000PP":500},{"TRELLIS_NAME":"10-19","SERIES_NAME":"MALE","X_CALENDAR_YEAR":2005,"Y_PREVALENCE_1000PP":285.7143},{"TRELLIS_NAME":"0-9","SERIES_NAME":"FEMALE","X_CALENDAR_YEAR":2005,"Y_PREVALENCE_1000PP":500},{"TRELLIS_NAME":"10-19","SERIES_NAME":"FEMALE","X_CALENDAR_YEAR":2005,"Y_PREVALENCE_1000PP":76.9231},{"TRELLIS_NAME":"0-9","SERIES_NAME":"MALE","X_CALENDAR_YEAR":2006,"Y_PREVALENCE_1000PP":750},{"TRELLIS_NAME":"0-9","SERIES_NAME":"FEMALE","X_CALENDAR_YEAR":2006,"Y_PREVALENCE_1000PP":454.5455},{"TRELLIS_NAME":"10-19","SERIES_NAME":"FEMALE","X_CALENDAR_YEAR":2006,"Y_PREVALENCE_1000PP":1000},{"TRELLIS_NAME":"10-19","SERIES_NAME":"MALE","X_CALENDAR_YEAR":2006,"Y_PREVALENCE_1000PP":1000},{"TRELLIS_NAME":"0-9","SERIES_NAME":"MALE","X_CALENDAR_YEAR":2008,"Y_PREVALENCE_1000PP":500},{"TRELLIS_NAME":"0-9","SERIES_NAME":"FEMALE","X_CALENDAR_YEAR":2008,"Y_PREVALENCE_1000PP":800},{"TRELLIS_NAME":"10-19","SERIES_NAME":"MALE","X_CALENDAR_YEAR":2008,"Y_PREVALENCE_1000PP":1000},{"TRELLIS_NAME":"10-19","SERIES_NAME":"FEMALE","X_CALENDAR_YEAR":2008,"Y_PREVALENCE_1000PP":1000},{"TRELLIS_NAME":"10-19","SERIES_NAME":"FEMALE","X_CALENDAR_YEAR":2010,"Y_PREVALENCE_1000PP":1000},{"TRELLIS_NAME":"0-9","SERIES_NAME":"FEMALE","X_CALENDAR_YEAR":2010,"Y_PREVALENCE_1000PP":909.0909},{"TRELLIS_NAME":"10-19","SERIES_NAME":"MALE","X_CALENDAR_YEAR":2010,"Y_PREVALENCE_1000PP":1000},{"TRELLIS_NAME":"0-9","SERIES_NAME":"MALE","X_CALENDAR_YEAR":2010,"Y_PREVALENCE_1000PP":750},{"TRELLIS_NAME":"10-19","SERIES_NAME":"MALE","X_CALENDAR_YEAR":2011,"Y_PREVALENCE_1000PP":1000},{"TRELLIS_NAME":"0-9","SERIES_NAME":"MALE","X_CALENDAR_YEAR":2011,"Y_PREVALENCE_1000PP":1000},{"TRELLIS_NAME":"20-29","SERIES_NAME":"FEMALE","X_CALENDAR_YEAR":2011,"Y_PREVALENCE_1000PP":125},{"TRELLIS_NAME":"0-9","SERIES_NAME":"FEMALE","X_CALENDAR_YEAR":2011,"Y_PREVALENCE_1000PP":777.7778},{"TRELLIS_NAME":"10-19","SERIES_NAME":"FEMALE","X_CALENDAR_YEAR":2011,"Y_PREVALENCE_1000PP":1000},{"TRELLIS_NAME":"10-19","SERIES_NAME":"FEMALE","X_CALENDAR_YEAR":2012,"Y_PREVALENCE_1000PP":1000},{"TRELLIS_NAME":"10-19","SERIES_NAME":"MALE","X_CALENDAR_YEAR":2012,"Y_PREVALENCE_1000PP":1000},{"TRELLIS_NAME":"0-9","SERIES_NAME":"FEMALE","X_CALENDAR_YEAR":2012,"Y_PREVALENCE_1000PP":625},{"TRELLIS_NAME":"20-29","SERIES_NAME":"FEMALE","X_CALENDAR_YEAR":2012,"Y_PREVALENCE_1000PP":200},{"TRELLIS_NAME":"0-9","SERIES_NAME":"MALE","X_CALENDAR_YEAR":2012,"Y_PREVALENCE_1000PP":750},{"TRELLIS_NAME":"0-9","SERIES_NAME":"FEMALE","X_CALENDAR_YEAR":2013,"Y_PREVALENCE_1000PP":1000},{"TRELLIS_NAME":"10-19","SERIES_NAME":"MALE","X_CALENDAR_YEAR":2013,"Y_PREVALENCE_1000PP":1000},{"TRELLIS_NAME":"0-9","SERIES_NAME":"MALE","X_CALENDAR_YEAR":2013,"Y_PREVALENCE_1000PP":600},{"TRELLIS_NAME":"10-19","SERIES_NAME":"FEMALE","X_CALENDAR_YEAR":2013,"Y_PREVALENCE_1000PP":1000},{"TRELLIS_NAME":"10-19","SERIES_NAME":"FEMALE","X_CALENDAR_YEAR":2014,"Y_PREVALENCE_1000PP":1000},{"TRELLIS_NAME":"10-19","SERIES_NAME":"MALE","X_CALENDAR_YEAR":2014,"Y_PREVALENCE_1000PP":1000},{"TRELLIS_NAME":"0-9","SERIES_NAME":"MALE","X_CALENDAR_YEAR":2014,"Y_PREVALENCE_1000PP":750},{"TRELLIS_NAME":"0-9","SERIES_NAME":"FEMALE","X_CALENDAR_YEAR":2014,"Y_PREVALENCE_1000PP":875},{"TRELLIS_NAME":"10-19","SERIES_NAME":"FEMALE","X_CALENDAR_YEAR":2017,"Y_PREVALENCE_1000PP":1000},{"TRELLIS_NAME":"20-29","SERIES_NAME":"FEMALE","X_CALENDAR_YEAR":2017,"Y_PREVALENCE_1000PP":76.9231},{"TRELLIS_NAME":"10-19","SERIES_NAME":"MALE","X_CALENDAR_YEAR":2017,"Y_PREVALENCE_1000PP":1000},{"TRELLIS_NAME":"0-9","SERIES_NAME":"MALE","X_CALENDAR_YEAR":2017,"Y_PREVALENCE_1000PP":750},{"TRELLIS_NAME":"0-9","SERIES_NAME":"FEMALE","X_CALENDAR_YEAR":2017,"Y_PREVALENCE_1000PP":1000},{"TRELLIS_NAME":"0-9","SERIES_NAME":"FEMALE","X_CALENDAR_YEAR":2018,"Y_PREVALENCE_1000PP":600},{"TRELLIS_NAME":"10-19","SERIES_NAME":"MALE","X_CALENDAR_YEAR":2018,"Y_PREVALENCE_1000PP":1000},{"TRELLIS_NAME":"0-9","SERIES_NAME":"MALE","X_CALENDAR_YEAR":2018,"Y_PREVALENCE_1000PP":500},{"TRELLIS_NAME":"10-19","SERIES_NAME":"FEMALE","X_CALENDAR_YEAR":2018,"Y_PREVALENCE_1000PP":1000},{"TRELLIS_NAME":"0-9","SERIES_NAME":"FEMALE","X_CALENDAR_YEAR":2020,"Y_PREVALENCE_1000PP":500},{"TRELLIS_NAME":"10-19","SERIES_NAME":"MALE","X_CALENDAR_YEAR":2020,"Y_PREVALENCE_1000PP":1000},{"TRELLIS_NAME":"10-19","SERIES_NAME":"FEMALE","X_CALENDAR_YEAR":2020,"Y_PREVALENCE_1000PP":1000},{"TRELLIS_NAME":"0-9","SERIES_NAME":"MALE","X_CALENDAR_YEAR":2020,"Y_PREVALENCE_1000PP":800},{"TRELLIS_NAME":"0-9","SERIES_NAME":"MALE","X_CALENDAR_YEAR":2021,"Y_PREVALENCE_1000PP":666.6667},{"TRELLIS_NAME":"10-19","SERIES_NAME":"FEMALE","X_CALENDAR_YEAR":2021,"Y_PREVALENCE_1000PP":1000},{"TRELLIS_NAME":"20-29","SERIES_NAME":"FEMALE","X_CALENDAR_YEAR":2021,"Y_PREVALENCE_1000PP":90.9091},{"TRELLIS_NAME":"10-19","SERIES_NAME":"MALE","X_CALENDAR_YEAR":2021,"Y_PREVALENCE_1000PP":1000},{"TRELLIS_NAME":"0-9","SERIES_NAME":"FEMALE","X_CALENDAR_YEAR":2021,"Y_PREVALENCE_1000PP":600},{"TRELLIS_NAME":"0-9","SERIES_NAME":"MALE","X_CALENDAR_YEAR":2023,"Y_PREVALENCE_1000PP":500},{"TRELLIS_NAME":"10-19","SERIES_NAME":"FEMALE","X_CALENDAR_YEAR":2023,"Y_PREVALENCE_1000PP":1000},{"TRELLIS_NAME":"0-9","SERIES_NAME":"FEMALE","X_CALENDAR_YEAR":2023,"Y_PREVALENCE_1000PP":1000},{"TRELLIS_NAME":"10-19","SERIES_NAME":"MALE","X_CALENDAR_YEAR":2023,"Y_PREVALENCE_1000PP":1000},{"TRELLIS_NAME":"10-19","SERIES_NAME":"FEMALE","X_CALENDAR_YEAR":2024,"Y_PREVALENCE_1000PP":875},{"TRELLIS_NAME":"0-9","SERIES_NAME":"MALE","X_CALENDAR_YEAR":2024,"Y_PREVALENCE_1000PP":666.6667},{"TRELLIS_NAME":"10-19","SERIES_NAME":"MALE","X_CALENDAR_YEAR":2024,"Y_PREVALENCE_1000PP":1000},{"TRELLIS_NAME":"0-9","SERIES_NAME":"FEMALE","X_CALENDAR_YEAR":2024,"Y_PREVALENCE_1000PP":800},{"TRELLIS_NAME":"10-19","SERIES_NAME":"MALE","X_CALENDAR_YEAR":2025,"Y_PREVALENCE_1000PP":500},{"TRELLIS_NAME":"0-9","SERIES_NAME":"MALE","X_CALENDAR_YEAR":2025,"Y_PREVALENCE_1000PP":714.2857},{"TRELLIS_NAME":"0-9","SERIES_NAME":"FEMALE","X_CALENDAR_YEAR":2025,"Y_PREVALENCE_1000PP":400},{"TRELLIS_NAME":"10-19","SERIES_NAME":"FEMALE","X_CALENDAR_YEAR":2025,"Y_PREVALENCE_1000PP":1000}],"PREVALENCE_BY_MONTH":[{"X_CALENDAR_MONTH":197404,"Y_PREVALENCE_1000PP":52.6316},{"X_CALENDAR_MONTH":197504,"Y_PREVALENCE_1000PP":47.6191},{"X_CALENDAR_MONTH":197604,"Y_PREVALENCE_1000PP":43.4783},{"X_CALENDAR_MONTH":197705,"Y_PREVALENCE_1000PP":40},{"X_CALENDAR_MONTH":200312,"Y_PREVALENCE_1000PP":15.1515},{"X_CALENDAR_MONTH":200401,"Y_PREVALENCE_1000PP":14.7059},{"X_CALENDAR_MONTH":200402,"Y_PREVALENCE_1000PP":14.7059},{"X_CALENDAR_MONTH":200404,"Y_PREVALENCE_1000PP":14.2857},{"X_CALENDAR_MONTH":200406,"Y_PREVALENCE_1000PP":14.2857},{"X_CALENDAR_MONTH":200407,"Y_PREVALENCE_1000PP":14.2857},{"X_CALENDAR_MONTH":200409,"Y_PREVALENCE_1000PP":14.2857},{"X_CALENDAR_MONTH":200410,"Y_PREVALENCE_1000PP":14.2857},{"X_CALENDAR_MONTH":200412,"Y_PREVALENCE_1000PP":14.2857},{"X_CALENDAR_MONTH":200501,"Y_PREVALENCE_1000PP":14.0845},{"X_CALENDAR_MONTH":200504,"Y_PREVALENCE_1000PP":14.0845},{"X_CALENDAR_MONTH":200507,"Y_PREVALENCE_1000PP":13.5135},{"X_CALENDAR_MONTH":200510,"Y_PREVALENCE_1000PP":38.961},{"X_CALENDAR_MONTH":200511,"Y_PREVALENCE_1000PP":25.974},{"X_CALENDAR_MONTH":200512,"Y_PREVALENCE_1000PP":12.987},{"X_CALENDAR_MONTH":200601,"Y_PREVALENCE_1000PP":38.4615},{"X_CALENDAR_MONTH":200602,"Y_PREVALENCE_1000PP":12.987},{"X_CALENDAR_MONTH":200603,"Y_PREVALENCE_1000PP":25.3165},{"X_CALENDAR_MONTH":200604,"Y_PREVALENCE_1000PP":24.6914},{"X_CALENDAR_MONTH":200605,"Y_PREVALENCE_1000PP":24.6914},{"X_CALENDAR_MONTH":200606,"Y_PREVALENCE_1000PP":61.7284},{"X_CALENDAR_MONTH":200607,"Y_PREVALENCE_1000PP":49.3827},{"X_CALENDAR_MONTH":200608,"Y_PREVALENCE_1000PP":12.1951},{"X_CALENDAR_MONTH":200609,"Y_PREVALENCE_1000PP":35.2941},{"X_CALENDAR_MONTH":200610,"Y_PREVALENCE_1000PP":47.0588},{"X_CALENDAR_MONTH":200611,"Y_PREVALENCE_1000PP":23.5294},{"X_CALENDAR_MONTH":200701,"Y_PREVALENCE_1000PP":35.2941},{"X_CALENDAR_MONTH":200702,"Y_PREVALENCE_1000PP":35.2941},{"X_CALENDAR_MONTH":200703,"Y_PREVALENCE_1000PP":23.5294},{"X_CALENDAR_MONTH":200704,"Y_PREVALENCE_1000PP":11.7647},{"X_CALENDAR_MONTH":200705,"Y_PREVALENCE_1000PP":47.0588},{"X_CALENDAR_MONTH":200706,"Y_PREVALENCE_1000PP":35.2941},{"X_CALENDAR_MONTH":200707,"Y_PREVALENCE_1000PP":70.5882},{"X_CALENDAR_MONTH":200708,"Y_PREVALENCE_1000PP":11.7647},{"X_CALENDAR_MONTH":200709,"Y_PREVALENCE_1000PP":47.0588},{"X_CALENDAR_MONTH":200710,"Y_PREVALENCE_1000PP":47.0588},{"X_CALENDAR_MONTH":200711,"Y_PREVALENCE_1000PP":35.2941},{"X_CALENDAR_MONTH":200801,"Y_PREVALENCE_1000PP":35.2941},{"X_CALENDAR_MONTH":200802,"Y_PREVALENCE_1000PP":23.5294},{"X_CALENDAR_MONTH":200803,"Y_PREVALENCE_1000PP":23.5294},{"X_CALENDAR_MONTH":200804,"Y_PREVALENCE_1000PP":23.2558},{"X_CALENDAR_MONTH":200805,"Y_PREVALENCE_1000PP":46.5116},{"X_CALENDAR_MONTH":200806,"Y_PREVALENCE_1000PP":46.5116},{"X_CALENDAR_MONTH":200807,"Y_PREVALENCE_1000PP":69.7674},{"X_CALENDAR_MONTH":200808,"Y_PREVALENCE_1000PP":22.9885},{"X_CALENDAR_MONTH":200809,"Y_PREVALENCE_1000PP":34.4828},{"X_CALENDAR_MONTH":200810,"Y_PREVALENCE_1000PP":34.4828},{"X_CALENDAR_MONTH":200811,"Y_PREVALENCE_1000PP":45.977},{"X_CALENDAR_MONTH":200812,"Y_PREVALENCE_1000PP":11.4942},{"X_CALENDAR_MONTH":200901,"Y_PREVALENCE_1000PP":34.4828},{"X_CALENDAR_MONTH":200902,"Y_PREVALENCE_1000PP":57.4713},{"X_CALENDAR_MONTH":200903,"Y_PREVALENCE_1000PP":11.4942},{"X_CALENDAR_MONTH":200904,"Y_PREVALENCE_1000PP":22.9885},{"X_CALENDAR_MONTH":200905,"Y_PREVALENCE_1000PP":22.9885},{"X_CALENDAR_MONTH":200906,"Y_PREVALENCE_1000PP":45.977},{"X_CALENDAR_MONTH":200907,"Y_PREVALENCE_1000PP":80.4598},{"X_CALENDAR_MONTH":200908,"Y_PREVALENCE_1000PP":45.977},{"X_CALENDAR_MONTH":200909,"Y_PREVALENCE_1000PP":11.4942},{"X_CALENDAR_MONTH":200910,"Y_PREVALENCE_1000PP":45.977},{"X_CALENDAR_MONTH":200911,"Y_PREVALENCE_1000PP":22.9885},{"X_CALENDAR_MONTH":200912,"Y_PREVALENCE_1000PP":11.4942},{"X_CALENDAR_MONTH":201001,"Y_PREVALENCE_1000PP":22.9885},{"X_CALENDAR_MONTH":201002,"Y_PREVALENCE_1000PP":80.4598},{"X_CALENDAR_MONTH":201004,"Y_PREVALENCE_1000PP":22.9885},{"X_CALENDAR_MONTH":201005,"Y_PREVALENCE_1000PP":11.4942},{"X_CALENDAR_MONTH":201006,"Y_PREVALENCE_1000PP":34.4828},{"X_CALENDAR_MONTH":201007,"Y_PREVALENCE_1000PP":57.4713},{"X_CALENDAR_MONTH":201008,"Y_PREVALENCE_1000PP":45.977},{"X_CALENDAR_MONTH":201009,"Y_PREVALENCE_1000PP":22.9885},{"X_CALENDAR_MONTH":201010,"Y_PREVALENCE_1000PP":34.4828},{"X_CALENDAR_MONTH":201011,"Y_PREVALENCE_1000PP":22.9885},{"X_CALENDAR_MONTH":201012,"Y_PREVALENCE_1000PP":22.7273},{"X_CALENDAR_MONTH":201101,"Y_PREVALENCE_1000PP":11.3636},{"X_CALENDAR_MONTH":201102,"Y_PREVALENCE_1000PP":34.0909},{"X_CALENDAR_MONTH":201103,"Y_PREVALENCE_1000PP":34.0909},{"X_CALENDAR_MONTH":201104,"Y_PREVALENCE_1000PP":22.7273},{"X_CALENDAR_MONTH":201105,"Y_PREVALENCE_1000PP":11.3636},{"X_CALENDAR_MONTH":201106,"Y_PREVALENCE_1000PP":11.3636},{"X_CALENDAR_MONTH":201107,"Y_PREVALENCE_1000PP":67.4157},{"X_CALENDAR_MONTH":201108,"Y_PREVALENCE_1000PP":78.6517},{"X_CALENDAR_MONTH":201109,"Y_PREVALENCE_1000PP":11.236},{"X_CALENDAR_MONTH":201110,"Y_PREVALENCE_1000PP":33.7079},{"X_CALENDAR_MONTH":201111,"Y_PREVALENCE_1000PP":11.236},{"X_CALENDAR_MONTH":201112,"Y_PREVALENCE_1000PP":22.4719},{"X_CALENDAR_MONTH":201201,"Y_PREVALENCE_1000PP":11.236},{"X_CALENDAR_MONTH":201202,"Y_PREVALENCE_1000PP":22.4719},{"X_CALENDAR_MONTH":201203,"Y_PREVALENCE_1000PP":33.7079},{"X_CALENDAR_MONTH":201204,"Y_PREVALENCE_1000PP":22.2222},{"X_CALENDAR_MONTH":201205,"Y_PREVALENCE_1000PP":11.1111},{"X_CALENDAR_MONTH":201206,"Y_PREVALENCE_1000PP":11.1111},{"X_CALENDAR_MONTH":201207,"Y_PREVALENCE_1000PP":33.3333},{"X_CALENDAR_MONTH":201208,"Y_PREVALENCE_1000PP":77.7778},{"X_CALENDAR_MONTH":201210,"Y_PREVALENCE_1000PP":22.2222},{"X_CALENDAR_MONTH":201211,"Y_PREVALENCE_1000PP":22.2222},{"X_CALENDAR_MONTH":201212,"Y_PREVALENCE_1000PP":11.1111},{"X_CALENDAR_MONTH":201301,"Y_PREVALENCE_1000PP":11.1111},{"X_CALENDAR_MONTH":201302,"Y_PREVALENCE_1000PP":11.1111},{"X_CALENDAR_MONTH":201303,"Y_PREVALENCE_1000PP":11.1111},{"X_CALENDAR_MONTH":201304,"Y_PREVALENCE_1000PP":11.1111},{"X_CALENDAR_MONTH":201305,"Y_PREVALENCE_1000PP":22.2222},{"X_CALENDAR_MONTH":201307,"Y_PREVALENCE_1000PP":11.1111},{"X_CALENDAR_MONTH":201308,"Y_PREVALENCE_1000PP":77.7778},{"X_CALENDAR_MONTH":201310,"Y_PREVALENCE_1000PP":21.978},{"X_CALENDAR_MONTH":201311,"Y_PREVALENCE_1000PP":33.3333},{"X_CALENDAR_MONTH":201312,"Y_PREVALENCE_1000PP":22.2222},{"X_CALENDAR_MONTH":201401,"Y_PREVALENCE_1000PP":11.1111},{"X_CALENDAR_MONTH":201402,"Y_PREVALENCE_1000PP":11.1111},{"X_CALENDAR_MONTH":201403,"Y_PREVALENCE_1000PP":22.2222},{"X_CALENDAR_MONTH":201405,"Y_PREVALENCE_1000PP":33.3333},{"X_CALENDAR_MONTH":201406,"Y_PREVALENCE_1000PP":10.989},{"X_CALENDAR_MONTH":201407,"Y_PREVALENCE_1000PP":10.989},{"X_CALENDAR_MONTH":201408,"Y_PREVALENCE_1000PP":54.9451},{"X_CALENDAR_MONTH":201409,"Y_PREVALENCE_1000PP":32.967},{"X_CALENDAR_MONTH":201410,"Y_PREVALENCE_1000PP":10.989},{"X_CALENDAR_MONTH":201411,"Y_PREVALENCE_1000PP":32.967},{"X_CALENDAR_MONTH":201412,"Y_PREVALENCE_1000PP":21.978},{"X_CALENDAR_MONTH":201501,"Y_PREVALENCE_1000PP":10.989},{"X_CALENDAR_MONTH":201503,"Y_PREVALENCE_1000PP":32.967},{"X_CALENDAR_MONTH":201505,"Y_PREVALENCE_1000PP":21.978},{"X_CALENDAR_MONTH":201506,"Y_PREVALENCE_1000PP":10.989},{"X_CALENDAR_MONTH":201507,"Y_PREVALENCE_1000PP":10.989},{"X_CALENDAR_MONTH":201508,"Y_PREVALENCE_1000PP":32.967},{"X_CALENDAR_MONTH":201509,"Y_PREVALENCE_1000PP":43.956},{"X_CALENDAR_MONTH":201510,"Y_PREVALENCE_1000PP":10.989},{"X_CALENDAR_MONTH":201511,"Y_PREVALENCE_1000PP":32.967},{"X_CALENDAR_MONTH":201512,"Y_PREVALENCE_1000PP":10.989},{"X_CALENDAR_MONTH":201601,"Y_PREVALENCE_1000PP":10.989},{"X_CALENDAR_MONTH":201603,"Y_PREVALENCE_1000PP":32.967},{"X_CALENDAR_MONTH":201604,"Y_PREVALENCE_1000PP":21.978},{"X_CALENDAR_MONTH":201605,"Y_PREVALENCE_1000PP":21.978},{"X_CALENDAR_MONTH":201606,"Y_PREVALENCE_1000PP":10.989},{"X_CALENDAR_MONTH":201608,"Y_PREVALENCE_1000PP":43.956},{"X_CALENDAR_MONTH":201609,"Y_PREVALENCE_1000PP":43.956},{"X_CALENDAR_MONTH":201610,"Y_PREVALENCE_1000PP":10.989},{"X_CALENDAR_MONTH":201611,"Y_PREVALENCE_1000PP":43.956},{"X_CALENDAR_MONTH":201612,"Y_PREVALENCE_1000PP":10.989},{"X_CALENDAR_MONTH":201701,"Y_PREVALENCE_1000PP":10.989},{"X_CALENDAR_MONTH":201702,"Y_PREVALENCE_1000PP":10.989},{"X_CALENDAR_MONTH":201703,"Y_PREVALENCE_1000PP":43.956},{"X_CALENDAR_MONTH":201704,"Y_PREVALENCE_1000PP":10.989},{"X_CALENDAR_MONTH":201705,"Y_PREVALENCE_1000PP":32.967},{"X_CALENDAR_MONTH":201706,"Y_PREVALENCE_1000PP":10.989},{"X_CALENDAR_MONTH":201708,"Y_PREVALENCE_1000PP":32.967},{"X_CALENDAR_MONTH":201709,"Y_PREVALENCE_1000PP":43.956},{"X_CALENDAR_MONTH":201711,"Y_PREVALENCE_1000PP":43.956},{"X_CALENDAR_MONTH":201712,"Y_PREVALENCE_1000PP":21.978},{"X_CALENDAR_MONTH":201802,"Y_PREVALENCE_1000PP":10.989},{"X_CALENDAR_MONTH":201803,"Y_PREVALENCE_1000PP":21.978},{"X_CALENDAR_MONTH":201804,"Y_PREVALENCE_1000PP":10.989},{"X_CALENDAR_MONTH":201805,"Y_PREVALENCE_1000PP":21.978},{"X_CALENDAR_MONTH":201806,"Y_PREVALENCE_1000PP":21.7391},{"X_CALENDAR_MONTH":201808,"Y_PREVALENCE_1000PP":10.8696},{"X_CALENDAR_MONTH":201809,"Y_PREVALENCE_1000PP":54.3478},{"X_CALENDAR_MONTH":201811,"Y_PREVALENCE_1000PP":10.7527},{"X_CALENDAR_MONTH":201812,"Y_PREVALENCE_1000PP":43.0108},{"X_CALENDAR_MONTH":201902,"Y_PREVALENCE_1000PP":10.7527},{"X_CALENDAR_MONTH":201903,"Y_PREVALENCE_1000PP":10.7527},{"X_CALENDAR_MONTH":201904,"Y_PREVALENCE_1000PP":32.2581},{"X_CALENDAR_MONTH":201906,"Y_PREVALENCE_1000PP":43.4783},{"X_CALENDAR_MONTH":201907,"Y_PREVALENCE_1000PP":21.7391},{"X_CALENDAR_MONTH":201908,"Y_PREVALENCE_1000PP":10.8696},{"X_CALENDAR_MONTH":201909,"Y_PREVALENCE_1000PP":32.6087},{"X_CALENDAR_MONTH":201910,"Y_PREVALENCE_1000PP":32.6087},{"X_CALENDAR_MONTH":201911,"Y_PREVALENCE_1000PP":10.8696},{"X_CALENDAR_MONTH":201912,"Y_PREVALENCE_1000PP":32.6087},{"X_CALENDAR_MONTH":202001,"Y_PREVALENCE_1000PP":21.7391},{"X_CALENDAR_MONTH":202002,"Y_PREVALENCE_1000PP":10.8696},{"X_CALENDAR_MONTH":202004,"Y_PREVALENCE_1000PP":32.6087},{"X_CALENDAR_MONTH":202006,"Y_PREVALENCE_1000PP":32.2581},{"X_CALENDAR_MONTH":202007,"Y_PREVALENCE_1000PP":43.0108},{"X_CALENDAR_MONTH":202008,"Y_PREVALENCE_1000PP":10.7527},{"X_CALENDAR_MONTH":202009,"Y_PREVALENCE_1000PP":31.9149},{"X_CALENDAR_MONTH":202010,"Y_PREVALENCE_1000PP":31.9149},{"X_CALENDAR_MONTH":202011,"Y_PREVALENCE_1000PP":10.6383},{"X_CALENDAR_MONTH":202012,"Y_PREVALENCE_1000PP":52.6316},{"X_CALENDAR_MONTH":202101,"Y_PREVALENCE_1000PP":31.5789},{"X_CALENDAR_MONTH":202102,"Y_PREVALENCE_1000PP":10.5263},{"X_CALENDAR_MONTH":202104,"Y_PREVALENCE_1000PP":31.5789},{"X_CALENDAR_MONTH":202105,"Y_PREVALENCE_1000PP":10.5263},{"X_CALENDAR_MONTH":202106,"Y_PREVALENCE_1000PP":31.5789},{"X_CALENDAR_MONTH":202107,"Y_PREVALENCE_1000PP":21.0526},{"X_CALENDAR_MONTH":202109,"Y_PREVALENCE_1000PP":31.5789},{"X_CALENDAR_MONTH":202110,"Y_PREVALENCE_1000PP":52.6316},{"X_CALENDAR_MONTH":202111,"Y_PREVALENCE_1000PP":10.5263},{"X_CALENDAR_MONTH":202112,"Y_PREVALENCE_1000PP":20.8333},{"X_CALENDAR_MONTH":202201,"Y_PREVALENCE_1000PP":20.8333},{"X_CALENDAR_MONTH":202202,"Y_PREVALENCE_1000PP":10.4167},{"X_CALENDAR_MONTH":202204,"Y_PREVALENCE_1000PP":31.25},{"X_CALENDAR_MONTH":202205,"Y_PREVALENCE_1000PP":20.8333},{"X_CALENDAR_MONTH":202206,"Y_PREVALENCE_1000PP":31.25},{"X_CALENDAR_MONTH":202207,"Y_PREVALENCE_1000PP":10.4167},{"X_CALENDAR_MONTH":202208,"Y_PREVALENCE_1000PP":10.4167},{"X_CALENDAR_MONTH":202209,"Y_PREVALENCE_1000PP":20.8333},{"X_CALENDAR_MONTH":202210,"Y_PREVALENCE_1000PP":41.6667},{"X_CALENDAR_MONTH":202212,"Y_PREVALENCE_1000PP":31.25},{"X_CALENDAR_MONTH":202301,"Y_PREVALENCE_1000PP":20.8333},{"X_CALENDAR_MONTH":202302,"Y_PREVALENCE_1000PP":10.4167},{"X_CALENDAR_MONTH":202303,"Y_PREVALENCE_1000PP":10.4167},{"X_CALENDAR_MONTH":202304,"Y_PREVALENCE_1000PP":20.8333},{"X_CALENDAR_MONTH":202305,"Y_PREVALENCE_1000PP":20.8333},{"X_CALENDAR_MONTH":202306,"Y_PREVALENCE_1000PP":51.5464},{"X_CALENDAR_MONTH":202307,"Y_PREVALENCE_1000PP":10.3093},{"X_CALENDAR_MONTH":202308,"Y_PREVALENCE_1000PP":10.3093},{"X_CALENDAR_MONTH":202310,"Y_PREVALENCE_1000PP":62.5},{"X_CALENDAR_MONTH":202311,"Y_PREVALENCE_1000PP":21.0526},{"X_CALENDAR_MONTH":202312,"Y_PREVALENCE_1000PP":31.5789},{"X_CALENDAR_MONTH":202401,"Y_PREVALENCE_1000PP":10.5263},{"X_CALENDAR_MONTH":202402,"Y_PREVALENCE_1000PP":21.2766},{"X_CALENDAR_MONTH":202403,"Y_PREVALENCE_1000PP":10.7527},{"X_CALENDAR_MONTH":202405,"Y_PREVALENCE_1000PP":53.1915},{"X_CALENDAR_MONTH":202406,"Y_PREVALENCE_1000PP":31.9149},{"X_CALENDAR_MONTH":202407,"Y_PREVALENCE_1000PP":10.8696},{"X_CALENDAR_MONTH":202408,"Y_PREVALENCE_1000PP":10.8696},{"X_CALENDAR_MONTH":202410,"Y_PREVALENCE_1000PP":56.8182},{"X_CALENDAR_MONTH":202411,"Y_PREVALENCE_1000PP":36.5854},{"X_CALENDAR_MONTH":202412,"Y_PREVALENCE_1000PP":12.5},{"X_CALENDAR_MONTH":202501,"Y_PREVALENCE_1000PP":12.987},{"X_CALENDAR_MONTH":202502,"Y_PREVALENCE_1000PP":27.7778},{"X_CALENDAR_MONTH":202503,"Y_PREVALENCE_1000PP":13.8889},{"X_CALENDAR_MONTH":202505,"Y_PREVALENCE_1000PP":63.4921},{"X_CALENDAR_MONTH":202506,"Y_PREVALENCE_1000PP":36.3636},{"X_CALENDAR_MONTH":202507,"Y_PREVALENCE_1000PP":42.5532},{"X_CALENDAR_MONTH":202508,"Y_PREVALENCE_1000PP":60.6061}],"FREQUENCY_DISTRIBUTION":[{"Y_NUM_PERSONS":47,"X_COUNT":1},{"Y_NUM_PERSONS":46,"X_COUNT":2},{"Y_NUM_PERSONS":45,"X_COUNT":3},{"Y_NUM_PERSONS":43,"X_COUNT":4},{"Y_NUM_PERSONS":39,"X_COUNT":5},{"Y_NUM_PERSONS":36,"X_COUNT":6},{"Y_NUM_PERSONS":32,"X_COUNT":7},{"Y_NUM_PERSONS":28,"X_COUNT":8},{"Y_NUM_PERSONS":23,"X_COUNT":9},{"Y_NUM_PERSONS":20,"X_COUNT":11},{"Y_NUM_PERSONS":19,"X_COUNT":12},{"Y_NUM_PERSONS":18,"X_COUNT":13},{"Y_NUM_PERSONS":16,"X_COUNT":14},{"Y_NUM_PERSONS":15,"X_COUNT":15},{"Y_NUM_PERSONS":11,"X_COUNT":16},{"Y_NUM_PERSONS":9,"X_COUNT":18},{"Y_NUM_PERSONS":8,"X_COUNT":19},{"Y_NUM_PERSONS":6,"X_COUNT":20},{"Y_NUM_PERSONS":3,"X_COUNT":21},{"Y_NUM_PERSONS":1,"X_COUNT":22}],"MEASUREMENTS_BY_TYPE":[{"CONCEPT_NAME":"EHR encounter record","COUNT_VALUE":540}],"AGE_AT_FIRST_OCCURRENCE":[{"CATEGORY":"MALE","MIN_VALUE":2,"P10_VALUE":2,"P25_VALUE":2,"MEDIAN_VALUE":3,"P75_VALUE":14,"P90_VALUE":17,"MAX_VALUE":18},{"CATEGORY":"FEMALE","MIN_VALUE":2,"P10_VALUE":2,"P25_VALUE":3,"MEDIAN_VALUE":4,"P75_VALUE":13,"P90_VALUE":15,"MAX_VALUE":17}],"RECORDS_BY_UNIT":[{"CONCEPT_NAME":"percent","COUNT_VALUE":540}],"MEASUREMENT_VALUE_DISTRIBUTION":[{"CATEGORY":"percent","MIN_VALUE":2.2,"P10_VALUE":23.2,"P25_VALUE":41.8,"MEDIAN_VALUE":64.1,"P75_VALUE":87.7,"P90_VALUE":94.5,"MAX_VALUE":100}],"LOWER_LIMIT_DISTRIBUTION":[],"UPPER_LIMIT_DISTRIBUTION":[],"VALUES_RELATIVE_TO_NORM":[]}
